tasklog/__init__.py
tasklog/__main__.py
tasklog/__version__.py
tasklog/cli.py
tasklog/commandexception.py
tasklog/constants.py
tasklog/helper/__init__.py
tasklog/helper/config.py
tasklog/helper/jira.py
tasklog/helper/logger.py
tasklog/helper/slack.py
tasklog/mock/__init__.py
tasklog/mock/mock_jira.py
tasklog/mock/mock_slack.py
tasklog/operations/__init__.py
tasklog/operations/common/__init__.py
tasklog/operations/common/generictasklog.py
tasklog/operations/common/tasklogoperation.py
tasklog/operations/common/tasklogoperationbuilder.py
tasklog/operations/common/tasklogparser.py
tasklog/operations/common/tasklograndom.py
tasklog/operations/common/tasklogreader.py
tasklog/operations/common/tasklogwriter.py
tasklog/operations/submitDaily/__init__.py
tasklog/operations/submitDaily/main.py
tasklog/operations/submitWorklog/__init__.py
tasklog/operations/submitWorklog/main.py
tasklog-0.0.12.dist-info/LICENSE
tasklog-0.0.12.dist-info/METADATA
tasklog-0.0.12.dist-info/WHEEL
tasklog-0.0.12.dist-info/entry_points.txt
tasklog-0.0.12.dist-info/top_level.txt
tasklog-0.0.12.dist-info/RECORD
