Metadata-Version: 2.1
Name: tasklog
Version: 0.0.12
Summary: CLI to submit tasklogs to Jira
Home-page: https://github.com/davidandreoletti/tasklog-cli
Author: David Andreoletti
Author-email: david.andreoletti.dev@gmail.com
License: UNKNOWN
Platform: UNKNOWN
Classifier: Programming Language :: Python :: 3
Classifier: License :: OSI Approved :: MIT License
Classifier: Operating System :: OS Independent
Requires-Python: >=3.7.3
Requires-Dist: PyYAML (>=3.11)
Requires-Dist: jira (>=2.0.0)
Requires-Dist: lark-parser (>=0.7.1)
Requires-Dist: pytimeparse (>=1.1.8)
Requires-Dist: python-dateutil (>=2.8.0)
Requires-Dist: slackclient (>=2.0.1)
Requires-Dist: will-natural (>=0.2.1.1)
